{
  "date": "6月17日（金）",
  "games": [
    {
      "url": "https://npb.jp/scores/2022/0617/s-c-07/",
      "home": "東京ヤクルトスワローズ",
      "road": "広島東洋カープ",
      "score": "7 - 2",
      "place": "神宮",
      "status": "試合終了"
    },
    {
      "url": "https://npb.jp/scores/2022/0617/d-g-10/",
      "home": "中日ドラゴンズ",
      "road": "読売ジャイアンツ",
      "score": "2 - 0",
      "place": "バンテリンドーム",
      "status": "試合終了"
    },
    {
      "url": "https://npb.jp/scores/2022/0617/t-db-08/",
      "home": "阪神タイガース",
      "road": "横浜DeNAベイスターズ",
      "score": "7 - 5",
      "place": "甲子園",
      "status": "試合終了"
    },
    {
      "url": "https://npb.jp/scores/2022/0617/f-m-07/",
      "home": "北海道日本ハムファイターズ",
      "road": "千葉ロッテマリーンズ",
      "score": "4 - 7",
      "place": "札幌ドーム",
      "status": "試合終了"
    },
    {
      "url": "https://npb.jp/scores/2022/0617/l-b-10/",
      "home": "埼玉西武ライオンズ",
      "road": "オリックス・バファローズ",
      "score": "4 - 2",
      "place": "ベルーナドーム",
      "status": "試合終了"
    },
    {
      "url": "https://npb.jp/scores/2022/0617/h-e-06/",
      "home": "福岡ソフトバンクホークス",
      "road": "東北楽天ゴールデンイーグルス",
      "score": "9 - 4",
      "place": "PayPayドーム",
      "status": "試合終了"
    }
  ]
}